npy_unittest/__init__.py
npy_unittest/_npy_unittest.py
npy_unittest-0.1.0.dist-info/METADATA
npy_unittest-0.1.0.dist-info/WHEEL
npy_unittest-0.1.0.dist-info/top_level.txt
npy_unittest-0.1.0.dist-info/RECORD
